jomfish/__init__.py
jomfish/wrapper.py
jomfish/bin/jomfish.exe
jomfish-10.0.dist-info/METADATA
jomfish-10.0.dist-info/WHEEL
jomfish-10.0.dist-info/entry_points.txt
jomfish-10.0.dist-info/top_level.txt
jomfish-10.0.dist-info/RECORD
