Metadata-Version: 2.2
Name: jomfish
Version: 10.0
Summary: Jomfish - A high-performance chess engine
Author: Jimmy Luong
Author-email: nguyenhungjimmy.luong@gmail.com
Classifier: Programming Language :: Rust
Classifier: Operating System :: Microsoft :: Windows
Requires-Python: >=3.6
Dynamic: author
Dynamic: author-email
Dynamic: classifier
Dynamic: description
Dynamic: description-content-type
Dynamic: requires-python
Dynamic: summary
